mycalc/calculator.py
mynewcalc-0.0.1.dist-info/LICENSE
mynewcalc-0.0.1.dist-info/METADATA
mynewcalc-0.0.1.dist-info/WHEEL
mynewcalc-0.0.1.dist-info/top_level.txt
mynewcalc-0.0.1.dist-info/RECORD
