Metadata-Version: 2.1
Name: mynewcalc
Version: 0.0.1
Summary: oss-dev my calculator 0001
Home-page: https://github.com/chunsejin/calc0001
Download-URL: https://github.com/chunsejin/calc0001
Author: sejinchun
Author-email: sjchun@dau.ac.kr
Classifier: Programming Language :: Python :: 3
Classifier: Operating System :: OS Independent
License-File: LICENSE
